<annotations><filename>00003228.JPEG</filename><folder>images</folder><size><width>224</width><height>224</height><depth>3</depth></size><object><name>lego gubbe</name><pose>Unspecified</pose><truncated>0</truncated><difficult>0</difficult><bndbox><xmin>80</xmin><ymin>98</ymin><xmax>138</xmax><ymax>176</ymax></bndbox></object><object><name>lego gubbe</name><pose>Unspecified</pose><truncated>0</truncated><difficult>0</difficult><bndbox><xmin>102</xmin><ymin>24</ymin><xmax>143</xmax><ymax>63</ymax></bndbox></object></annotations>