<annotations><filename>00004138.JPEG</filename><folder>images</folder><size><width>224</width><height>224</height><depth>3</depth></size><object><name>lego gubbe</name><pose>Unspecified</pose><truncated>0</truncated><difficult>0</difficult><bndbox><xmin>159</xmin><ymin>6</ymin><xmax>201</xmax><ymax>44</ymax></bndbox></object><object><name>lego gubbe</name><pose>Unspecified</pose><truncated>0</truncated><difficult>0</difficult><bndbox><xmin>91</xmin><ymin>59</ymin><xmax>193</xmax><ymax>165</ymax></bndbox></object></annotations>